sus2ymst/__init__.py
sus2ymst/__main__.py
sus2ymst/cli.py
sus2ymst/convert.py
sus2ymst/types.py
sus2ymst-0.0.4.dist-info/LICENSE
sus2ymst-0.0.4.dist-info/METADATA
sus2ymst-0.0.4.dist-info/WHEEL
sus2ymst-0.0.4.dist-info/entry_points.txt
sus2ymst-0.0.4.dist-info/top_level.txt
sus2ymst-0.0.4.dist-info/RECORD
