Metadata-Version: 2.1
Name: sus2ymst
Version: 0.0.4
Summary: Convert Ched SUS to YMST(world dai star) txt chart format.
Home-page: https://github.com/k0tayan/sus2ymst
Author: k0tayan
Author-email: kotayan0415@outlook.jp
Classifier: Programming Language :: Python :: 3
Classifier: License :: OSI Approved :: MIT License
Requires-Python: >=3.9
License-File: LICENSE
Requires-Dist: sus-io
